[
    {
        "PSSMLT": {
            "MAPE": {
                "val": "0.3020",
                "fc": "PSSMLT-MAPE.png"
            },
            "MRSE": {
                "val": "0.1326",
                "fc": "PSSMLT-MRSE.png"
            }
        }
    },
    {
        "MMLT": {
            "MAPE": {
                "val": "0.3020",
                "fc": "MMLT-MAPE.png"
            },
            "MRSE": {
                "val": "0.1326",
                "fc": "MMLT-MRSE.png"
            }
        }
    }
]